plasnet/ColorPicker.py
plasnet/Templates.py
plasnet/__init__.py
plasnet/__main__.py
plasnet/base_graph.py
plasnet/communities.py
plasnet/community_graph.py
plasnet/ext/libs/bluebird.js
plasnet/ext/libs/cytoscape-bubblesets.js
plasnet/ext/libs/cytoscape-euler.js
plasnet/ext/libs/cytoscape-layers.js
plasnet/ext/libs/cytoscape-ngraph.forcelayout.js
plasnet/ext/libs/cytoscape.min.js
plasnet/ext/libs/fetch.min.js
plasnet/ext/libs/jquery-3.6.0.min.js
plasnet/ext/libs/jquery-ui.min.css
plasnet/ext/libs/jquery-ui.min.js
plasnet/ext/libs/jquery-ui.structure.min.css
plasnet/ext/libs/jquery-ui.theme.min.css
plasnet/ext/libs/jquery.blockUI.js
plasnet/ext/libs/jquery.layout-1.4.0.js
plasnet/ext/libs/resources/images/busy.gif
plasnet/ext/libs/resources/images/ui-icons_444444_256x240.png
plasnet/ext/libs/resources/images/ui-icons_555555_256x240.png
plasnet/ext/libs/resources/images/ui-icons_777620_256x240.png
plasnet/ext/libs/resources/images/ui-icons_777777_256x240.png
plasnet/ext/libs/resources/images/ui-icons_cc0000_256x240.png
plasnet/ext/libs/resources/images/ui-icons_ffffff_256x240.png
plasnet/ext/libs/style.css
plasnet/ext/templates/index_template.html
plasnet/ext/templates/plasnet_style.xml
plasnet/ext/templates/visualisation_template.html
plasnet/hub_graph.py
plasnet/list_of_graphs.py
plasnet/output_producer.py
plasnet/plasmid_graph.py
plasnet/plasnet_main.py
plasnet/sample_graph.py
plasnet/sample_graphs.py
plasnet/subcommunities.py
plasnet/subcommunity_graph.py
plasnet/utils.py
plasnet-0.6.0.dist-info/LICENSE
plasnet-0.6.0.dist-info/METADATA
plasnet-0.6.0.dist-info/WHEEL
plasnet-0.6.0.dist-info/entry_points.txt
plasnet-0.6.0.dist-info/RECORD
