Metadata-Version: 2.1
Name: plasnet
Version: 0.6.0
Summary: Clustering, visualising and exploring plasmid networks
Home-page: https://github.com/leoisl/plasnet
License: MIT
Keywords: Plasmids,Networks,Graphs,Clustering,Visualisation,Exploration
Author: Leandro Lima
Author-email: leandro@ebi.ac.uk
Requires-Python: >=3.9,<3.13
Classifier: License :: OSI Approved :: MIT License
Classifier: Programming Language :: Python :: 3
Classifier: Programming Language :: Python :: 3.9
Classifier: Programming Language :: Python :: 3.10
Classifier: Programming Language :: Python :: 3.11
Classifier: Programming Language :: Python :: 3.12
Requires-Dist: click (>=8.1.7,<9.0.0)
Requires-Dist: networkx (>=3.2,<4.0)
Requires-Dist: pandas (>=2.1.2,<3.0.0)
Project-URL: Repository, https://github.com/leoisl/plasnet
